Workbook

Sheet Cleaned Dataset
A1: Customer ID | B1: Full Name | C1: Age | D1: Gender | E1: Country | F1: Product Category | G1: Purchase Date | H1: Units Sold | I1: Unit Price (USD) | J1: Total Revenue (USD) | K1: Payment Method | L1: Customer Segment | M1: Churn Flag | N1: Satisfaction Score (1-5)
A2: C001 | B2: Aarav Shah | C2: 28 | D2: Male | E2: India | F2: Electronics | G2: 2024-01-05 | H2: 3 | I2: 149.99 | J2: =H2*I2 | K2: UPI | L2: Premium | M2: 0 | N2: 4.5
A3: C002 | B3: Priya Mehta | C3: 34 | D3: Female | E3: India | F3: Clothing | G3: 2024-01-08 | H3: 5 | I3: 39.99 | J3: =H3*I3 | K3: Credit Card | L3: Regular | M3: 0 | N3: 3.8
A4: C003 | B4: James Carter | C4: 45 | D4: Male | E4: USA | F4: Electronics | G4: 2024-01-12 | H4: 2 | I4: 299.99 | J4: =H4*I4 | K4: Debit Card | L4: Premium | M4: 0 | N4: 5
A5: C004 | B5: Li Wei | C5: 22 | D5: Female | E5: China | F5: Books | G5: 2024-01-15 | H5: 8 | I5: 12.5 | J5: =H5*I5 | K5: PayPal | L5: Budget | M5: 0 | N5: 4.2
A6: C005 | B6: Maria Garcia | C6: 31 | D6: Female | E6: Spain | F6: Beauty | G6: 2024-01-18 | H6: 4 | I6: 24.99 | J6: =H6*I6 | K6: Credit Card | L6: Regular | M6: 0 | N6: 4
A7: C006 | B7: Riya Patel | C7: 27 | D7: Female | E7: India | F7: Sports | G7: 2024-01-20 | H7: 6 | I7: 59.99 | J7: =H7*I7 | K7: UPI | L7: Regular | M7: 0 | N7: 3.5
A8: C007 | B8: David Kim | C8: 39 | D8: Male | E8: South Korea | F8: Electronics | G8: 2024-01-22 | H8: 1 | I8: 899.99 | J8: =H8*I8 | K8: Credit Card | L8: Premium | M8: 0 | N8: 4.8
A9: C008 | B9: Fatima Al-Sayed | C9: 52 | D9: Female | E9: UAE | F9: Clothing | G9: 2024-01-25 | H9: 3 | I9: 89.99 | J9: =H9*I9 | K9: Credit Card | L9: Premium | M9: 1 | N9: 2.5
A10: C009 | B10: Chen Jing | C10: 29 | D10: Male | E10: China | F10: Food & Beverage | G10: 2024-02-01 | H10: 12 | I10: 8.99 | J10: =H10*I10 | K10: Alipay | L10: Budget | M10: 0 | N10: 4.1
A11: C010 | B11: Sophie Mueller | C11: 44 | D11: Female | E11: Germany | F11: Books | G11: 2024-02-03 | H11: 2 | I11: 29.99 | J11: =H11*I11 | K11: PayPal | L11: Regular | M11: 0 | N11: 3.9
A12: C011 | B12: Arjun Nair | C12: 33 | D12: Male | E12: India | F12: Electronics | G12: 2024-02-07 | H12: 2 | I12: 199.99 | J12: =H12*I12 | K12: UPI | L12: Regular | M12: 0 | N12: 4.3
A13: C012 | B13: Emma Thompson | C13: 26 | D13: Female | E13: UK | F13: Beauty | G13: 2024-02-10 | H13: 7 | I13: 18.5 | J13: =H13*I13 | K13: Debit Card | L13: Budget | M13: 0 | N13: 3.7
... A21: C020 | B21: Isabelle Dupont | C21: 43 | D21: Female | E21: France | F21: Clothing | G21: 2024-03-15 | H21: 5 | I21: 65.99 | J21: =H21*I21 | K21: Credit Card | L21: Regular | M21: 1 | N21: 2.2

Sheet Summary Statistics
A1: Metric | B1: Value | C1: Details | D1: Source
A2: Dataset Overview
A3: Total Records | B3: 20 | C3: Rows of customer data | D3: Cleaned Dataset
A4: Total Features | B4: 14 | C4: Columns / Variables | D4: Cleaned Dataset
A5: Missing Values | B5: 0 | C5: After cleaning | D5: Cleaned Dataset
A6: Duplicate Records | B6: 0 | C6: Removed during cleaning | D6: Cleaned Dataset
A7: Date Range | B7: Jan-Mar 2024 | C7: 3-month period | D7: Cleaned Dataset
A9: Revenue Metrics
A10: Total Revenue (USD) | B10: =SUM('Cleaned Dataset'!J2:J21) | C10: All transactions | D10: Cleaned Dataset
A11: Avg Revenue / Order | B11: =AVERAGE('Cleaned Dataset'!J2:J21) | C11: Mean order value | D11: Cleaned Dataset
A12: Max Revenue / Order | B12: =MAX('Cleaned Dataset'!J2:J21) | C12: Highest order | D12: Cleaned Dataset
A13: Min Revenue / Order | B13: =MIN('Cleaned Dataset'!J2:J21) | C13: Lowest order | D13: Cleaned Dataset
A15: Customer Metrics
A16: Average Customer Age | B16: =AVERAGE('Cleaned Dataset'!C2:C21) | C16: Years | D16: Cleaned Dataset
A17: Churn Rate (%) | B17: =COUNTIF('Cleaned Dataset'!M2:M21,1)/20*100 | C17: % churned | D17: Cleaned Dataset
A18: Avg Satisfaction Score | B18: =AVERAGE('Cleaned Dataset'!N2:N21) | C18: Out of 5 | D18: Cleaned Dataset
A19: Premium Customers | B19: =COUNTIF('Cleaned Dataset'!L2:L21,"Premium") | C19: Count | D19: Cleaned Dataset
A20: Budget Customers | B20: =COUNTIF('Cleaned Dataset'!L2:L21,"Budget") | C20: Count | D20: Cleaned Dataset
A22: Data Cleaning Steps Applied
A23: 1. Removed duplicates | B23: 0 found | C23: Validated via Customer ID | D23: Pre-processing
A24: 2. Standardised date format | B24: YYYY-MM-DD | C24: ISO 8601 standard applied | D24: Pre-processing
A25: 3. Handled missing values | B25: 0 remaining | C25: Dataset is complete | D25: Pre-processing
A26: 4. Corrected data types | B26: All correct | C26: Numeric / Text / Date types | D26: Pre-processing
A27: 5. Computed Total Revenue | B27: New column | C27: Units Sold x Unit Price | D27: Feature Engineering
A28: 6. Customer segmentation | B28: 3 segments | C28: Premium / Regular / Budget | D28: Feature Engineering
A29: 7. Added churn binary flag | B29: 0 or 1 | C29: 1 = churned, 0 = retained | D29: Feature Engineering
